FLOCK_GPS/ClusteringFeats.py
FLOCK_GPS/DataLoading.py
FLOCK_GPS/DirectionalCorrelation.py
FLOCK_GPS/PACS.py
FLOCK_GPS/PacsFeats.py
FLOCK_GPS/Preprocessing.py
FLOCK_GPS/RegularityFeats.py
FLOCK_GPS/SpatialFeats.py
FLOCK_GPS/VelocityFeats.py
FLOCK_GPS/__init__.py
flock_gps-0.0.2.dist-info/METADATA
flock_gps-0.0.2.dist-info/WHEEL
flock_gps-0.0.2.dist-info/licenses/LICENSE
flock_gps-0.0.2.dist-info/RECORD
