Metadata-Version: 2.3
Name: FLOCK_GPS
Version: 0.0.2
Summary: A package for extracting metrics from group movement GPS data
Project-URL: Homepage, https://github.com/Tufts-University/FLOCK
Project-URL: Issues, https://github.com/Tufts-University/FLOCK/issues
Author-email: James McIntyre <james_mcintyre@uri.edu>
License-File: LICENSE
Keywords: GPS,Group Dynamics,Group Movement,Human Performance Prediction,Machine Learning
Classifier: Development Status :: 3 - Alpha
Classifier: License :: OSI Approved :: MIT License
Classifier: Operating System :: OS Independent
Classifier: Programming Language :: Python :: 3
Requires-Python: >=3.8
Requires-Dist: entropyhub>=0.2
Requires-Dist: folium>=0.14.0
Requires-Dist: hdbscan>=0.8.29
Requires-Dist: ipykernel>=6.27.1
Requires-Dist: matplotlib>=3.4.3
Requires-Dist: movingpandas>=0.15rc1
Requires-Dist: networkx>=0.13.5
Requires-Dist: numpy>=1.24.4
Requires-Dist: pandas>=1.5.3
Requires-Dist: pillow>=9.4.0
Requires-Dist: plotly>=5.13.0
Requires-Dist: scikit-image>=0.21.0
Requires-Dist: scikit-learn>=1.1.2
Requires-Dist: scipy>=1.11.3
Requires-Dist: seaborn>=0.11.2
Requires-Dist: shapely>=2.0.0
Requires-Dist: statsmodels>=0.13.5
Requires-Dist: tqdm>=4.64.1
